risc-v(rv32i)/rtl/memory/data_ram.v
`timescale 1ns/1ps

module data_ram #(
    parameter BYTES = 1024
) (
    input  wire        clk,
    input  wire [31:0] addr,
    input  wire [31:0] wdata,
    input  wire [3:0]  wstrb,
    output wire [31:0] rdata
);
    reg [7:0] mem [0:BYTES-1];
    integer i;

    initial begin
        for (i = 0; i < BYTES; i = i + 1)
            mem[i] = 8'd0;
    end

    assign rdata = {
        mem[addr + 32'd3],
        mem[addr + 32'd2],
        mem[addr + 32'd1],
        mem[addr]
    };

    always @(posedge clk) begin
        if (wstrb[0]) mem[addr]         <= wdata[7:0];
        if (wstrb[1]) mem[addr + 32'd1] <= wdata[15:8];
        if (wstrb[2]) mem[addr + 32'd2] <= wdata[23:16];
        if (wstrb[3]) mem[addr + 32'd3] <= wdata[31:24];
    end
endmodule

risc-v(rv32i)/rtl/memory/instruction_rom.v
`timescale 1ns/1ps

module instruction_rom #(
    parameter WORDS = 256,
    parameter INIT_FILE = "programs/demo.hex"
) (
    input  wire [31:0] addr,
    output wire [31:0] rdata
);
    reg [31:0] mem [0:WORDS-1];

    initial begin
        $readmemh(INIT_FILE, mem);
    end

    assign rdata = mem[addr[9:2]];
endmodule

risc-v(rv32i)/rtl/core/rv32_lsu.v
`timescale 1ns/1ps

module rv32_lsu (
    input  wire        store_enable,
    input  wire [1:0]  size,
    input  wire        unsigned_load,
    input  wire [31:0] store_value,
    input  wire [31:0] memory_value,
    output reg  [3:0]  write_strobe,
    output reg  [31:0] write_data,
    output reg  [31:0] load_data
);
    always @(*) begin
        write_strobe = 4'b0000;
        write_data   = store_value;

        if (store_enable) begin
            case (size)
                2'd0: write_strobe = 4'b0001; // SB
                2'd1: write_strobe = 4'b0011; // SH
                default: write_strobe = 4'b1111; // SW
            endcase
        end

        case (size)
            2'd0: begin
                if (unsigned_load)
                    load_data = {24'd0, memory_value[7:0]};
                else
                    load_data = {{24{memory_value[7]}}, memory_value[7:0]};
            end
            2'd1: begin
                if (unsigned_load)
                    load_data = {16'd0, memory_value[15:0]};
                else
                    load_data = {{16{memory_value[15]}}, memory_value[15:0]};
            end
            default: load_data = memory_value;
        endcase
    end
endmodule

risc-v(rv32i)/rtl/core/rv32_branch.v
`timescale 1ns/1ps

module rv32_branch (
    input  wire        enable,
    input  wire [2:0]  funct3,
    input  wire [31:0] left,
    input  wire [31:0] right,
    output reg         take
);
    always @(*) begin
        take = 1'b0;
        if (enable) begin
            case (funct3)
                3'b000: take = (left == right);                    // BEQ
                3'b001: take = (left != right);                    // BNE
                3'b100: take = ($signed(left) < $signed(right));   // BLT
                3'b101: take = ($signed(left) >= $signed(right));  // BGE
                3'b110: take = (left < right);                     // BLTU
                3'b111: take = (left >= right);                    // BGEU
                default: take = 1'b0;
            endcase
        end
    end
endmodule

risc-v(rv32i)/rtl/core/rv32_alu.v
`timescale 1ns/1ps

module rv32_alu (
    input  wire [31:0] a,
    input  wire [31:0] b,
    input  wire [3:0]  op,
    output reg  [31:0] y
);
    localparam ALU_ADD  = 4'd0;
    localparam ALU_SUB  = 4'd1;
    localparam ALU_AND  = 4'd2;
    localparam ALU_OR   = 4'd3;
    localparam ALU_XOR  = 4'd4;
    localparam ALU_SLL  = 4'd5;
    localparam ALU_SRL  = 4'd6;
    localparam ALU_SRA  = 4'd7;
    localparam ALU_SLT  = 4'd8;
    localparam ALU_SLTU = 4'd9;
    localparam ALU_PASS = 4'd10;

    always @(*) begin
        case (op)
            ALU_ADD : y = a + b;
            ALU_SUB : y = a - b;
            ALU_AND : y = a & b;
            ALU_OR  : y = a | b;
            ALU_XOR : y = a ^ b;
            ALU_SLL : y = a << b[4:0];
            ALU_SRL : y = a >> b[4:0];
            ALU_SRA : y = $signed(a) >>> b[4:0];
            ALU_SLT : y = ($signed(a) < $signed(b)) ? 32'd1 : 32'd0;
            ALU_SLTU: y = (a < b) ? 32'd1 : 32'd0;
            ALU_PASS: y = b;
            default : y = 32'd0;
        endcase
    end
endmodule

risc-v(rv32i)/rtl/core/rv32_regfile.v
`timescale 1ns/1ps

module rv32_regfile (
    input  wire        clk,
    input  wire        rst_n,
    input  wire        write_enable,
    input  wire [4:0]  rs1,
    input  wire [4:0]  rs2,
    input  wire [4:0]  rd,
    input  wire [31:0] write_data,
    output wire [31:0] rs1_data,
    output wire [31:0] rs2_data
);
    reg [31:0] regs [0:31];
    integer i;

    assign rs1_data = (rs1 == 5'd0) ? 32'd0 : regs[rs1];
    assign rs2_data = (rs2 == 5'd0) ? 32'd0 : regs[rs2];

    always @(posedge clk) begin
        if (!rst_n) begin
            for (i = 0; i < 32; i = i + 1)
                regs[i] <= 32'd0;
        end else if (write_enable && (rd != 5'd0)) begin
            regs[rd] <= write_data;
        end

        regs[0] <= 32'd0;
    end
endmodule

risc-v(rv32i)/rtl/core/rv32_immediate.v
`timescale 1ns/1ps

module rv32_immediate (
    input  wire [31:0] instruction,
    input  wire [2:0]  kind,
    output reg  [31:0] immediate
);
    localparam IMM_I = 3'd0;
    localparam IMM_S = 3'd1;
    localparam IMM_B = 3'd2;
    localparam IMM_U = 3'd3;
    localparam IMM_J = 3'd4;

    always @(*) begin
        case (kind)
            IMM_I: immediate = {{20{instruction[31]}}, instruction[31:20]};
            IMM_S: immediate = {{20{instruction[31]}}, instruction[31:25], instruction[11:7]};
            IMM_B: immediate = {{19{instruction[31]}}, instruction[31], instruction[7],
                                instruction[30:25], instruction[11:8], 1'b0};
            IMM_U: immediate = {instruction[31:12], 12'b0};
            IMM_J: immediate = {{11{instruction[31]}}, instruction[31], instruction[19:12],
                                instruction[20], instruction[30:21], 1'b0};
            default: immediate = 32'd0;
        endcase
    end
endmodule

risc-v(rv32i)/rtl/core/rv32_decoder.v
`timescale 1ns/1ps

module rv32_decoder (
    input  wire [6:0] opcode,
    input  wire [2:0] funct3,
    input  wire       funct7_bit5,

    output reg        reg_write,
    output reg        src_a_pc,
    output reg        src_b_imm,
    output reg [3:0]  alu_op,
    output reg [2:0]  imm_kind,
    output reg [1:0]  wb_select,
    output reg        mem_write,
    output reg [1:0]  mem_size,
    output reg        load_unsigned,
    output reg        branch_enable,
    output reg        jal,
    output reg        jalr
);
    localparam ALU_ADD  = 4'd0;
    localparam ALU_SUB  = 4'd1;
    localparam ALU_AND  = 4'd2;
    localparam ALU_OR   = 4'd3;
    localparam ALU_XOR  = 4'd4;
    localparam ALU_SLL  = 4'd5;
    localparam ALU_SRL  = 4'd6;
    localparam ALU_SRA  = 4'd7;
    localparam ALU_SLT  = 4'd8;
    localparam ALU_SLTU = 4'd9;
    localparam ALU_PASS = 4'd10;

    localparam IMM_I = 3'd0;
    localparam IMM_S = 3'd1;
    localparam IMM_B = 3'd2;
    localparam IMM_U = 3'd3;
    localparam IMM_J = 3'd4;

    localparam WB_ALU = 2'd0;
    localparam WB_MEM = 2'd1;
    localparam WB_PC4 = 2'd2;

    always @(*) begin
        reg_write     = 1'b0;
        src_a_pc      = 1'b0;
        src_b_imm     = 1'b0;
        alu_op        = ALU_ADD;
        imm_kind      = IMM_I;
        wb_select     = WB_ALU;
        mem_write     = 1'b0;
        mem_size      = 2'd2;
        load_unsigned = 1'b0;
        branch_enable = 1'b0;
        jal           = 1'b0;
        jalr          = 1'b0;

        case (opcode)
            7'b0110011: begin // R-type
                reg_write = 1'b1;
                case (funct3)
                    3'b000: alu_op = funct7_bit5 ? ALU_SUB : ALU_ADD;
                    3'b001: alu_op = ALU_SLL;
                    3'b010: alu_op = ALU_SLT;
                    3'b011: alu_op = ALU_SLTU;
                    3'b100: alu_op = ALU_XOR;
                    3'b101: alu_op = funct7_bit5 ? ALU_SRA : ALU_SRL;
                    3'b110: alu_op = ALU_OR;
                    3'b111: alu_op = ALU_AND;
                    default: alu_op = ALU_ADD;
                endcase
            end

            7'b0010011: begin // I-type arithmetic
                reg_write = 1'b1;
                src_b_imm = 1'b1;
                imm_kind  = IMM_I;
                case (funct3)
                    3'b000: alu_op = ALU_ADD;
                    3'b010: alu_op = ALU_SLT;
                    3'b011: alu_op = ALU_SLTU;
                    3'b100: alu_op = ALU_XOR;
                    3'b110: alu_op = ALU_OR;
                    3'b111: alu_op = ALU_AND;
                    3'b001: alu_op = ALU_SLL;
                    3'b101: alu_op = funct7_bit5 ? ALU_SRA : ALU_SRL;
                    default: alu_op = ALU_ADD;
                endcase
            end

            7'b0000011: begin // Loads
                reg_write = 1'b1;
                src_b_imm = 1'b1;
                imm_kind  = IMM_I;
                alu_op    = ALU_ADD;
                wb_select = WB_MEM;
                case (funct3)
                    3'b000: begin mem_size = 2'd0; load_unsigned = 1'b0; end // LB
                    3'b001: begin mem_size = 2'd1; load_unsigned = 1'b0; end // LH
                    3'b010: begin mem_size = 2'd2; load_unsigned = 1'b0; end // LW
                    3'b100: begin mem_size = 2'd0; load_unsigned = 1'b1; end // LBU
                    3'b101: begin mem_size = 2'd1; load_unsigned = 1'b1; end // LHU
                    default: reg_write = 1'b0;
                endcase
            end

            7'b0100011: begin // Stores
                src_b_imm = 1'b1;
                imm_kind  = IMM_S;
                alu_op    = ALU_ADD;
                mem_write = 1'b1;
                case (funct3)
                    3'b000: mem_size = 2'd0; // SB
                    3'b001: mem_size = 2'd1; // SH
                    3'b010: mem_size = 2'd2; // SW
                    default: mem_write = 1'b0;
                endcase
            end

            7'b1100011: begin // Branches
                imm_kind      = IMM_B;
                branch_enable = 1'b1;
            end

            7'b1101111: begin // JAL
                reg_write = 1'b1;
                imm_kind  = IMM_J;
                wb_select = WB_PC4;
                jal       = 1'b1;
            end

            7'b1100111: begin // JALR
                reg_write = 1'b1;
                src_b_imm = 1'b1;
                imm_kind  = IMM_I;
                wb_select = WB_PC4;
                alu_op    = ALU_ADD;
                jalr      = 1'b1;
            end

            7'b0110111: begin // LUI
                reg_write = 1'b1;
                src_b_imm = 1'b1;
                imm_kind  = IMM_U;
                alu_op    = ALU_PASS;
            end

            7'b0010111: begin // AUIPC
                reg_write = 1'b1;
                src_a_pc  = 1'b1;
                src_b_imm = 1'b1;
                imm_kind  = IMM_U;
                alu_op    = ALU_ADD;
            end

            default: begin
                // Unsupported instruction behaves like NOP.
            end
        endcase
    end
endmodule

risc-v(rv32i)/rtl/core/rv32_core.v
`timescale 1ns/1ps

module rv32_core (
    input  wire        clk,
    input  wire        rst_n,

    output wire [31:0] instr_addr,
    input  wire [31:0] instr_data,

    output wire [31:0] data_addr,
    output wire [31:0] data_wdata,
    output wire [3:0]  data_wstrb,
    input  wire [31:0] data_rdata
);
    reg [31:0] pc;
    reg [31:0] next_pc;
    reg [31:0] writeback;

    wire [6:0] opcode = instr_data[6:0];
    wire [4:0] rd     = instr_data[11:7];
    wire [2:0] funct3 = instr_data[14:12];
    wire [4:0] rs1    = instr_data[19:15];
    wire [4:0] rs2    = instr_data[24:20];
    wire       funct7_bit5 = instr_data[30];

    wire       reg_write;
    wire       src_a_pc;
    wire       src_b_imm;
    wire [3:0] alu_op;
    wire [2:0] imm_kind;
    wire [1:0] wb_select;
    wire       mem_write;
    wire [1:0] mem_size;
    wire       load_unsigned;
    wire       branch_enable;
    wire       jal;
    wire       jalr;

    wire [31:0] imm_value;
    wire [31:0] rs1_value;
    wire [31:0] rs2_value;
    wire [31:0] alu_a;
    wire [31:0] alu_b;
    wire [31:0] alu_result;
    wire        branch_take;
    wire [31:0] load_data;
    wire [31:0] pc_plus_4 = pc + 32'd4;

    assign instr_addr = pc;
    assign alu_a = src_a_pc ? pc : rs1_value;
    assign alu_b = src_b_imm ? imm_value : rs2_value;
    assign data_addr = alu_result;

    rv32_decoder decode (
        .opcode(opcode),
        .funct3(funct3),
        .funct7_bit5(funct7_bit5),
        .reg_write(reg_write),
        .src_a_pc(src_a_pc),
        .src_b_imm(src_b_imm),
        .alu_op(alu_op),
        .imm_kind(imm_kind),
        .wb_select(wb_select),
        .mem_write(mem_write),
        .mem_size(mem_size),
        .load_unsigned(load_unsigned),
        .branch_enable(branch_enable),
        .jal(jal),
        .jalr(jalr)
    );

    rv32_immediate imm_decode (
        .instruction(instr_data),
        .kind(imm_kind),
        .immediate(imm_value)
    );

    rv32_regfile rf (
        .clk(clk),
        .rst_n(rst_n),
        .write_enable(reg_write),
        .rs1(rs1),
        .rs2(rs2),
        .rd(rd),
        .write_data(writeback),
        .rs1_data(rs1_value),
        .rs2_data(rs2_value)
    );

    rv32_alu execute_alu (
        .a(alu_a),
        .b(alu_b),
        .op(alu_op),
        .y(alu_result)
    );

    rv32_branch branch_check (
        .enable(branch_enable),
        .funct3(funct3),
        .left(rs1_value),
        .right(rs2_value),
        .take(branch_take)
    );

    rv32_lsu lsu (
        .store_enable(mem_write),
        .size(mem_size),
        .unsigned_load(load_unsigned),
        .store_value(rs2_value),
        .memory_value(data_rdata),
        .write_strobe(data_wstrb),
        .write_data(data_wdata),
        .load_data(load_data)
    );

    always @(*) begin
        case (wb_select)
            2'd1: writeback = load_data;
            2'd2: writeback = pc_plus_4;
            default: writeback = alu_result;
        endcase
    end

    always @(*) begin
        next_pc = pc_plus_4;

        if (branch_enable && branch_take)
            next_pc = pc + imm_value;

        if (jal)
            next_pc = pc + imm_value;

        if (jalr)
            next_pc = (rs1_value + imm_value) & 32'hffff_fffe;
    end

    always @(posedge clk) begin
        if (!rst_n)
            pc <= 32'd0;
        else
            pc <= next_pc;
    end
endmodule

risc-v(rv32i)/rtl/rv32_lab_top.v
`timescale 1ns/1ps

module rv32_lab_top (
    input wire clk,
    input wire rst_n
);
    wire [31:0] i_addr;
    wire [31:0] i_data;
    wire [31:0] d_addr;
    wire [31:0] d_wdata;
    wire [3:0]  d_wstrb;
    wire [31:0] d_rdata;

    rv32_core core (
        .clk(clk),
        .rst_n(rst_n),
        .instr_addr(i_addr),
        .instr_data(i_data),
        .data_addr(d_addr),
        .data_wdata(d_wdata),
        .data_wstrb(d_wstrb),
        .data_rdata(d_rdata)
    );

    instruction_rom rom (
        .addr(i_addr),
        .rdata(i_data)
    );

    data_ram ram (
        .clk(clk),
        .addr(d_addr),
        .wdata(d_wdata),
        .wstrb(d_wstrb),
        .rdata(d_rdata)
    );
endmodule

risc-v(rv32i)/sim/tb_rv32_lab.v
`timescale 1ns/1ps

module tb_rv32_lab;
    reg clk;
    reg rst_n;
    integer cycles;

    rv32_lab_top dut (
        .clk(clk),
        .rst_n(rst_n)
    );

    initial begin
        clk = 1'b0;
        forever #5 clk = ~clk;
    end

    initial begin
        $dumpfile("build/rv32_trace.vcd");
        $dumpvars(0, tb_rv32_lab);

        rst_n = 1'b0;
        repeat (2) @(posedge clk);
        rst_n = 1'b1;

        for (cycles = 0; cycles < 20; cycles = cycles + 1)
            @(posedge clk);

        $display("x5  = %0d", dut.core.rf.regs[5]);
        $display("x6  = %0d", dut.core.rf.regs[6]);
        $display("x7  = %0d", dut.core.rf.regs[7]);
        $display("x8  = %0d", dut.core.rf.regs[8]);
        $display("x9  = %0d", dut.core.rf.regs[9]);
        $display("x10 = %0d", dut.core.rf.regs[10]);
        $display("RAM[128] = %0d", {dut.ram.mem[131], dut.ram.mem[130], dut.ram.mem[129], dut.ram.mem[128]});

        if ((dut.core.rf.regs[10] == 32'd42) &&
            ({dut.ram.mem[131], dut.ram.mem[130], dut.ram.mem[129], dut.ram.mem[128]} == 32'd25))
            $display("TEST PASSED");
        else
            $display("TEST FAILED");

        $finish;
    end
endmodule

risc-v(rv32i)/build/rv32_trace.vcd
$date
	Wed Aug 19 21:33:43 2026
$end
$version
	Icarus Verilog
$end
$timescale
	1ps
$end
$scope module tb_rv32_lab $end
$var reg 1 ! clk $end
$var reg 1 " rst_n $end
$var integer 32 # cycles [31:0] $end
$scope module dut $end
$var wire 1 ! clk $end
$var wire 1 " rst_n $end
$var wire 32 $ i_data [31:0] $end
$var wire 32 % i_addr [31:0] $end
$var wire 4 & d_wstrb [3:0] $end
$var wire 32 ' d_wdata [31:0] $end
$var wire 32 ( d_rdata [31:0] $end
$var wire 32 ) d_addr [31:0] $end
$scope module core $end
$var wire 1 ! clk $end
$var wire 32 * data_addr [31:0] $end
$var wire 32 + instr_addr [31:0] $end
$var wire 1 " rst_n $end
$var wire 2 , wb_select [1:0] $end
$var wire 1 - src_b_imm $end
$var wire 1 . src_a_pc $end
$var wire 32 / rs2_value [31:0] $end
$var wire 5 0 rs2 [4:0] $end
$var wire 32 1 rs1_value [31:0] $end
$var wire 5 2 rs1 [4:0] $end
$var wire 1 3 reg_write $end
$var wire 5 4 rd [4:0] $end
$var wire 32 5 pc_plus_4 [31:0] $end
$var wire 7 6 opcode [6:0] $end
$var wire 1 7 mem_write $end
$var wire 2 8 mem_size [1:0] $end
$var wire 1 9 load_unsigned $end
$var wire 32 : load_data [31:0] $end
$var wire 1 ; jalr $end
$var wire 1 < jal $end
$var wire 32 = instr_data [31:0] $end
$var wire 32 > imm_value [31:0] $end
$var wire 3 ? imm_kind [2:0] $end
$var wire 1 @ funct7_bit5 $end
$var wire 3 A funct3 [2:0] $end
$var wire 4 B data_wstrb [3:0] $end
$var wire 32 C data_wdata [31:0] $end
$var wire 32 D data_rdata [31:0] $end
$var wire 1 E branch_take $end
$var wire 1 F branch_enable $end
$var wire 32 G alu_result [31:0] $end
$var wire 4 H alu_op [3:0] $end
$var wire 32 I alu_b [31:0] $end
$var wire 32 J alu_a [31:0] $end
$var reg 32 K next_pc [31:0] $end
$var reg 32 L pc [31:0] $end
$var reg 32 M writeback [31:0] $end
$scope module branch_check $end
$var wire 3 N funct3 [2:0] $end
$var wire 32 O right [31:0] $end
$var wire 32 P left [31:0] $end
$var wire 1 F enable $end
$var reg 1 E take $end
$upscope $end
$scope module decode $end
$var wire 3 Q funct3 [2:0] $end
$var wire 1 @ funct7_bit5 $end
$var wire 7 R opcode [6:0] $end
$var parameter 4 S ALU_ADD $end
$var parameter 4 T ALU_AND $end
$var parameter 4 U ALU_OR $end
$var parameter 4 V ALU_PASS $end
$var parameter 4 W ALU_SLL $end
$var parameter 4 X ALU_SLT $end
$var parameter 4 Y ALU_SLTU $end
$var parameter 4 Z ALU_SRA $end
$var parameter 4 [ ALU_SRL $end
$var parameter 4 \ ALU_SUB $end
$var parameter 4 ] ALU_XOR $end
$var parameter 3 ^ IMM_B $end
$var parameter 3 _ IMM_I $end
$var parameter 3 ` IMM_J $end
$var parameter 3 a IMM_S $end
$var parameter 3 b IMM_U $end
$var parameter 2 c WB_ALU $end
$var parameter 2 d WB_MEM $end
$var parameter 2 e WB_PC4 $end
$var reg 4 f alu_op [3:0] $end
$var reg 1 F branch_enable $end
$var reg 3 g imm_kind [2:0] $end
$var reg 1 < jal $end
$var reg 1 ; jalr $end
$var reg 1 9 load_unsigned $end
$var reg 2 h mem_size [1:0] $end
$var reg 1 7 mem_write $end
$var reg 1 3 reg_write $end
$var reg 1 . src_a_pc $end
$var reg 1 - src_b_imm $end
$var reg 2 i wb_select [1:0] $end
$upscope $end
$scope module execute_alu $end
$var wire 32 j a [31:0] $end
$var wire 32 k b [31:0] $end
$var wire 4 l op [3:0] $end
$var parameter 4 m ALU_ADD $end
$var parameter 4 n ALU_AND $end
$var parameter 4 o ALU_OR $end
$var parameter 4 p ALU_PASS $end
$var parameter 4 q ALU_SLL $end
$var parameter 4 r ALU_SLT $end
$var parameter 4 s ALU_SLTU $end
$var parameter 4 t ALU_SRA $end
$var parameter 4 u ALU_SRL $end
$var parameter 4 v ALU_SUB $end
$var parameter 4 w ALU_XOR $end
$var reg 32 x y [31:0] $end
$upscope $end
$scope module imm_decode $end
$var wire 3 y kind [2:0] $end
$var wire 32 z instruction [31:0] $end
$var parameter 3 { IMM_B $end
$var parameter 3 | IMM_I $end
$var parameter 3 } IMM_J $end
$var parameter 3 ~ IMM_S $end
$var parameter 3 !" IMM_U $end
$var reg 32 "" immediate [31:0] $end
$upscope $end
$scope module lsu $end
$var wire 2 #" size [1:0] $end
$var wire 1 7 store_enable $end
$var wire 1 9 unsigned_load $end
$var wire 32 $" store_value [31:0] $end
$var wire 32 %" memory_value [31:0] $end
$var reg 32 &" load_data [31:0] $end
$var reg 32 '" write_data [31:0] $end
$var reg 4 (" write_strobe [3:0] $end
$upscope $end
$scope module rf $end
$var wire 1 ! clk $end
$var wire 5 )" rd [4:0] $end
$var wire 5 *" rs1 [4:0] $end
$var wire 5 +" rs2 [4:0] $end
$var wire 1 " rst_n $end
$var wire 32 ," write_data [31:0] $end
$var wire 1 3 write_enable $end
$var wire 32 -" rs2_data [31:0] $end
$var wire 32 ." rs1_data [31:0] $end
$var integer 32 /" i [31:0] $end
$upscope $end
$upscope $end
$scope module ram $end
$var wire 32 0" addr [31:0] $end
$var wire 1 ! clk $end
$var wire 32 1" wdata [31:0] $end
$var wire 4 2" wstrb [3:0] $end
$var wire 32 3" rdata [31:0] $end
$var parameter 32 4" BYTES $end
$var integer 32 5" i [31:0] $end
$upscope $end
$scope module rom $end
$var wire 32 6" addr [31:0] $end
$var wire 32 7" rdata [31:0] $end
$var parameter 136 8" INIT_FILE $end
$var parameter 32 9" WORDS $end
$upscope $end
$upscope $end
$upscope $end
$enddefinitions $end
$comment Show the parameter values. $end
$dumpall
b100000000 9"
b111000001110010011011110110011101110010011000010110110101110011001011110110010001100101011011010110111100101110011010000110010101111000 8"
b10000000000 4"
b11 !"
b1 ~
b100 }
b0 |
b10 {
b100 w
b1 v
b110 u
b111 t
b1001 s
b1000 r
b101 q
b1010 p
b11 o
b10 n
b0 m
b10 e
b1 d
b0 c
b11 b
b1 a
b100 `
b0 _
b10 ^
b100 ]
b1 \
b110 [
b111 Z
b1001 Y
b1000 X
b101 W
b1010 V
b11 U
b10 T
b0 S
$end
#0
$dumpvars
bx 7"
bx 6"
b10000000000 5"
bx 3"
bx 2"
bx 1"
bx 0"
bx /"
bx ."
bx -"
bx ,"
bx +"
bx *"
bx )"
bx ("
bx '"
bx &"
bx %"
bx $"
bx #"
bx ""
bx z
bx y
bx x
bx l
bx k
bx j
bx i
bx h
bx g
bx f
bx R
bx Q
bx P
bx O
bx N
bx M
bx L
bx K
bx J
bx I
bx H
bx G
xF
xE
bx D
bx C
bx B
bx A
x@
bx ?
bx >
bx =
x<
x;
bx :
x9
bx 8
x7
bx 6
bx 5
bx 4
x3
bx 2
bx 1
bx 0
bx /
x.
x-
bx ,
bx +
bx *
bx )
bx (
bx '
bx &
bx %
bx $
bx #
0"
0!
$end
#5000
b0 :
b0 &"
b0 '
b0 C
b0 '"
b0 1"
b0 &
b0 B
b0 ("
b0 2"
b111 M
b111 ,"
b0 (
b0 D
b0 %"
b0 3"
b111 )
b111 *
b111 0"
b111 G
b111 x
b111 I
b111 k
b0 J
b0 j
b0 /
b0 O
b0 $"
b0 -"
b0 1
b0 P
b0 ."
0E
0;
0<
0F
09
b10 8
b10 h
b10 #"
07
b0 ,
b0 i
b0 ?
b0 g
b0 y
b0 H
b0 f
b0 l
1-
0.
13
0@
b111 0
b111 +"
b0 2
b0 *"
b0 A
b0 N
b0 Q
b101 4
b101 )"
b10011 6
b10011 R
b111 >
b111 ""
b100 K
b11100000000001010010011 $
b11100000000001010010011 =
b11100000000001010010011 z
b11100000000001010010011 7"
b100 5
b0 %
b0 +
b0 6"
b0 L
b100000 /"
1!
#10000
0!
#15000
b0 #
1"
b100000 /"
1!
#20000
0!
#25000
b11 M
b11 ,"
b11 )
b11 *
b11 0"
b11 G
b11 x
b11 I
b11 k
b11 0
b11 +"
b110 4
b110 )"
b11 >
b11 ""
b1000 K
b1100000000001100010011 $
b1100000000001100010011 =
b1100000000001100010011 z
b1100000000001100010011 7"
b1000 5
b100 %
b100 +
b100 6"
b100 L
b1 #
1!
#30000
0!
#35000
b11100 M
b11100 ,"
b111 J
b111 j
b11100 )
b11100 *
b11100 0"
b11100 G
b11100 x
b111 1
b111 P
b111 ."
b101 H
b101 f
b101 l
1-
13
b10 I
b10 k
b10 0
b10 +"
b101 2
b101 *"
b1 A
b1 N
b1 Q
b111 4
b111 )"
b10 >
b10 ""
b1100 K
b1000101001001110010011 $
b1000101001001110010011 =
b1000101001001110010011 z
b1000101001001110010011 7"
b1100 5
b1000 %
b1000 +
b1000 6"
b1000 L
b10 #
1!
#40000
0!
#45000
b11001 M
b11001 ,"
b0 :
b0 &"
b11 '
b11 C
b11 '"
b11 1"
b11100 J
b11100 j
b0 (
b0 D
b0 %"
b0 3"
b11001 )
b11001 *
b11001 0"
b11001 G
b11001 x
b11 /
b11 O
b11 $"
b11 -"
b11100 1
b11100 P
b11100 ."
b1 H
b1 f
b1 l
0-
13
b11 I
b11 k
1@
b110 0
b110 +"
b111 2
b111 *"
b0 A
b0 N
b0 Q
b1000 4
b1000 )"
b110011 6
b110011 R
b10000000110 >
b10000000110 ""
b10000 K
b1000000011000111000010000110011 $
b1000000011000111000010000110011 =
b1000000011000111000010000110011 z
b1000000011000111000010000110011 7"
b10000 5
b1100 %
b1100 +
b1100 6"
b1100 L
b11 #
1!
#50000
0!
#55000
b10000000 M
b10000000 ,"
b0 J
b0 j
b1111 &
b1111 B
b1111 ("
b1111 2"
b11001 '
b11001 C
b11001 '"
b11001 1"
b10000000 I
b10000000 k
b10000000 )
b10000000 *
b10000000 0"
b10000000 G
b10000000 x
b11001 /
b11001 O
b11001 $"
b11001 -"
b0 1
b0 P
b0 ."
17
b1 ?
b1 g
b1 y
1-
b0 H
b0 f
b0 l
03
0@
b1000 0
b1000 +"
b0 2
b0 *"
b10 A
b10 N
b10 Q
b0 4
b0 )"
b100011 6
b100011 R
b10000000 >
b10000000 ""
b10100 K
b1000100000000010000000100011 $
b1000100000000010000000100011 =
b1000100000000010000000100011 z
b1000100000000010000000100011 7"
b10100 5
b10000 %
b10000 +
b10000 6"
b10000 L
b100 #
1!
#60000
0!
#65000
b11001 M
b11001 ,"
b0 '
b0 C
b0 '"
b0 1"
b10000000 )
b10000000 *
b10000000 0"
b10000000 G
b10000000 x
b0 /
b0 O
b0 $"
b0 -"
b1 ,
b1 i
13
07
b0 ?
b0 g
b0 y
1-
b10000000 I
b10000000 k
b0 0
b0 +"
b1001 4
b1001 )"
b11 6
b11 R
b10000000 >
b10000000 ""
b11000 K
b1000000000000010010010000011 $
b1000000000000010010010000011 =
b1000000000000010010010000011 z
b1000000000000010010010000011 7"
b11001 :
b11001 &"
b0 &
b0 B
b0 ("
b0 2"
b11000 5
b10100 %
b10100 +
b10100 6"
b10100 L
b11001 (
b11001 D
b11001 %"
b11001 3"
b101 #
1!
#70000
0!
#75000
b0 :
b0 &"
b11001 '
b11001 C
b11001 '"
b11001 1"
b11001 J
b11001 j
b110010 M
b110010 ,"
b0 (
b0 D
b0 %"
b0 3"
b110010 )
b110010 *
b110010 0"
b110010 G
b110010 x
b11001 /
b11001 O
b11001 $"
b11001 -"
b11001 1
b11001 P
b11001 ."
1E
1F
b10 ?
b10 g
b10 y
b0 ,
b0 i
0-
03
b11001 I
b11001 k
b1000 0
b1000 +"
b1001 2
b1001 *"
b0 A
b0 N
b0 Q
b1000 4
b1000 )"
b1100011 6
b1100011 R
b1000 >
b1000 ""
b100000 K
b100001001000010001100011 $
b100001001000010001100011 =
b100001001000010001100011 z
b100001001000010001100011 7"
b11100 5
b11000 %
b11000 +
b11000 6"
b11000 L
b110 #
1!
#80000
0!
#85000
b101010 M
b101010 ,"
b101010 )
b101010 *
b101010 0"
b101010 G
b101010 x
b0 '
b0 C
b0 '"
b0 1"
b0 J
b0 j
b101010 I
b101010 k
0E
b0 /
b0 O
b0 $"
b0 -"
b0 1
b0 P
b0 ."
1-
13
0F
b0 ?
b0 g
b0 y
b1010 0
b1010 +"
b0 2
b0 *"
b1010 4
b1010 )"
b10011 6
b10011 R
b101010 >
b101010 ""
b100100 K
b10101000000000010100010011 $
b10101000000000010100010011 =
b10101000000000010100010011 z
b10101000000000010100010011 7"
b100100 5
b100000 %
b100000 +
b100000 6"
b100000 L
b111 #
1!
#90000
0!
#95000
b101000 M
b101000 ,"
b0 )
b0 *
b0 0"
b0 G
b0 x
1<
b10 ,
b10 i
b100 ?
b100 g
b100 y
0-
13
b0 I
b0 k
b0 0
b0 +"
b0 4
b0 )"
b1101111 6
b1101111 R
b0 >
b0 ""
b0 '
b0 C
b0 '"
b0 1"
b100100 K
b1101111 $
b1101111 =
b1101111 z
b1101111 7"
b0 /
b0 O
b0 $"
b0 -"
b101000 5
b100100 %
b100100 +
b100100 6"
b100100 L
b1000 #
1!
#100000
0!
#105000
b1001 #
1!
#110000
0!
#115000
b1010 #
1!
#120000
0!
#125000
b1011 #
1!
#130000
0!
#135000
b1100 #
1!
#140000
0!
#145000
b1101 #
1!
#150000
0!
#155000
b1110 #
1!
#160000
0!
#165000
b1111 #
1!
#170000
0!
#175000
b10000 #
1!
#180000
0!
#185000
b10001 #
1!
#190000
0!
#195000
b10010 #
1!
#200000
0!
#205000
b10011 #
1!
#210000
0!
#215000
b10100 #
1!
